f_fee_tui/__init__.py
f_fee_tui/__main__.py
f_fee_tui/_help_screen.py
f_fee_tui/_master_screen.py
f_fee_tui/_queue.py
f_fee_tui/_version.py
f_fee_tui/aeb_command.py
f_fee_tui/aeb_state.py
f_fee_tui/app.py
f_fee_tui/app.tcss
f_fee_tui/deb_command.py
f_fee_tui/deb_mode.py
f_fee_tui/dialogs.py
f_fee_tui/dtc_in_mod.py
f_fee_tui/general_command.py
f_fee_tui/help.md
f_fee_tui/infobar.py
f_fee_tui/leds.py
f_fee_tui/messages.py
f_fee_tui/services.py
f_fee_tui/workers.py
f_fee_tui-0.7.2.dist-info/METADATA
f_fee_tui-0.7.2.dist-info/WHEEL
f_fee_tui-0.7.2.dist-info/entry_points.txt
f_fee_tui-0.7.2.dist-info/RECORD
