Metadata-Version: 2.3
Name: f-fee-tui
Version: 0.7.2
Summary: A Terminal User Interface to monitor and command the F-FEE for the PLATO Camera.
Author: Rik Huygen
License: MIT
Keywords: F-FEE,PLATO,Textual
Requires-Python: >=3.8
Requires-Dist: textual
